cosim_toolbox/__init__.py
cosim_toolbox/_commands.py
cosim_toolbox/_version.py
cosim_toolbox/dbms/__init__.py
cosim_toolbox/dbms/abstractions.py
cosim_toolbox/dbms/csv_timeseries.py
cosim_toolbox/dbms/factories.py
cosim_toolbox/dbms/json_metadata.py
cosim_toolbox/dbms/mongo_metadata.py
cosim_toolbox/dbms/postgresql_timeseries.py
cosim_toolbox/dbms/validation.py
cosim_toolbox/sims/__init__.py
cosim_toolbox/sims/bench_profile.py
cosim_toolbox/sims/dockerRunner.py
cosim_toolbox/sims/federate.py
cosim_toolbox/sims/federateLogger.py
cosim_toolbox/sims/federation.py
cosim_toolbox/sims/helicsConfig.py
cosim_toolbox-1.0.0.dist-info/licenses/LICENSE
dbms/__init__.py
dbms/abstractions.py
dbms/csv_timeseries.py
dbms/factories.py
dbms/json_metadata.py
dbms/mongo_metadata.py
dbms/postgresql_timeseries.py
dbms/validation.py
integration_tests/__init__.py
integration_tests/_test_simple_federation2.py
integration_tests/test_federate.py
integration_tests/test_simple_federation.py
sims/__init__.py
sims/bench_profile.py
sims/dockerRunner.py
sims/federate.py
sims/federateLogger.py
sims/federation.py
sims/helicsConfig.py
tests/__init__.py
tests/_test_federate_unit.py
tests/_test_federate_unit2.py
tests/conftest.py
tests/test_comprehensive_data_management.py
tests/test_csv_timeseries.py
tests/test_data_management.py
tests/test_federateLogger.py
tests/test_helicsConfig.py
tests/test_integration.py
tests/test_json_implementation.py
tests/test_json_metadata.py
tests/test_metadata_factory.py
tests/test_mongo_metadata.py
tests/test_performance.py
tests/test_postgresql_factory.py
tests/test_quick_verification.py
cosim_toolbox-1.0.0.dist-info/METADATA
cosim_toolbox-1.0.0.dist-info/WHEEL
cosim_toolbox-1.0.0.dist-info/entry_points.txt
cosim_toolbox-1.0.0.dist-info/top_level.txt
cosim_toolbox-1.0.0.dist-info/RECORD
