Metadata-Version: 2.4
Name: cosim_toolbox
Version: 1.0.0
Summary: Python support for the CoSimulation Toolbox
Author-email: Trevor Hardy <trevor.hardy@pnnl.gov>
Maintainer-email: Mitch Pelton <mitch.pelton@pnnl.gov>, Fred Rutz <fredrick.rutz@pnnl.gov>, Nathan Gray <nathan.gray@pnnl.gov>, Trevor Hardy <trevor.hardy@pnnl.gov>
License-Expression: BSD-2-Clause
Project-URL: Documentation, https://cosim_toolbox.readthedocs.io
Project-URL: Repository, https://github.com/pnnl/cst
Keywords: power system,transactive,energy
Classifier: Development Status :: 4 - Beta
Classifier: Environment :: Console
Classifier: Intended Audience :: Developers
Classifier: Intended Audience :: Education
Classifier: Intended Audience :: Science/Research
Classifier: Natural Language :: English
Classifier: Operating System :: OS Independent
Classifier: Programming Language :: Python
Classifier: Programming Language :: Python :: 3.10
Classifier: Topic :: Scientific/Engineering
Requires-Python: >=3.10
License-File: LICENSE
Requires-Dist: helics~=3.6.1
Requires-Dist: pandas~=2.3.1
Requires-Dist: psycopg2-binary~=2.9.10
Requires-Dist: pymongo~=4.13.2
Dynamic: license-file
